oceansat/__init__.py
oceansat/commandline.py
oceansat/export_production.py
oceansat-0.1.1.dist-info/entry_points.txt
oceansat-0.1.1.dist-info/LICENSE
oceansat-0.1.1.dist-info/WHEEL
oceansat-0.1.1.dist-info/METADATA
oceansat-0.1.1.dist-info/RECORD
