Metadata-Version: 2.1
Name: oceansat
Version: 0.1.1
Summary: 
Author: Bror Jonsson
Author-email: brorfred@gmail.com
Requires-Python: >=3.7,<4.0
Classifier: Programming Language :: Python :: 3
Classifier: Programming Language :: Python :: 3.7
Classifier: Programming Language :: Python :: 3.8
Requires-Dist: numpy (>=1.20.1,<2.0.0)
Requires-Dist: scipy (>=1.6.1,<2.0.0)
